<?xml version="1.0" encoding="UTF-8"?>
<!-- 
This sample dataset holds the complete information needed to set-up a visualization for the BO's ENE project. 
Authors: Christian Danowski, Benno Schmidt, Department of Geodesy, Bochum University of Applied Sciences.
-->
<Dataset version="0.1" xsi:noNamespaceSchemaLocation="xsd/Dataset.xsd" xmlns:xsi="http://www.w3.org/2001/XMLSchema-instance">
	<GeneralInformation>
		<Theme>
			<Title language="EN">Gas Resources</Title><!-- Titel bezogen auf die Sprache: Englisch-->
			<Title language="DE">Gas Ressourcen</Title><!-- Titel bezogen auf die Sprache: Deutsch-->
			<Description language="EN">This dataset gives the gas resources for the year 2012 for the World's countries.</Description><!-- Erklaerung auf Englisch-->
			<Description language="DE">Dieser Datensatz enthaelt staatenweise die Erdgasressourcen fuer das Jahr 2012.</Description><!-- Erklaerung auf Deutsch-->
		</Theme>
		<Unit>
			<Title>Billion m³ (Giga cubic meters)</Title><!-- Einheiten auf welche sich die gegebenen Daten beziehen: Englisch-->
			<Code>Gm³/a</Code><!-- Einheiten Kodiert-->
		</Unit>
		<PublicReference>BGR - Bundesanstalt fuer Geowissenschaften und Rohstoffe</PublicReference>
		<MetadataReference>GasResources_meta.xml</MetadataReference><!-- Referenz der Metadatendatei-->
	</GeneralInformation>
	<TableStructure>
		<Property dataType="ENE:iso3166-2" uniqueID="true"><!-- Hier verwendete Kodierliste bezueglich der Laenderkuerzel-->
			<Title>Country code</Title><!-- Titel-->
			<Description>Country code ISO 3166-2</Description><!-- For geo-referenced 
properties, a GeoReference element should be present: -->
			<GeoReference featureType="ENE:CountryCode" externalGeometries="true">
				<CRS>ENE:CountriesWorldwide:iso3166-2</CRS>
			</GeoReference>
		</Property>
		<Property dataType="Float">
			<Title>Extraction</Title>
			<Description language="DE">Foerderung oder Abbau des Rohstoffs.</Description>
		</Property>
		<Property dataType="Float">
			<Title>Cumulated extraction</Title>
			<Description language="DE">Kumulierte Foerderung; sprich wie viel Rohstoff wurde in allen Jahren seit Beginn der Foerderung abgebaut.</Description>
		</Property>
		<Property dataType="Float">
			<Title>Reserves</Title>
			<Description language="DE">Rohstoffreserven, sprich Menge an Rohstoff, der nach Stand der heutigen Technik noch abgebaut werden kann.</Description>
		</Property>
		<Property dataType="Float">
			<Title>Resources</Title>
			<Description language="DE">Rohstoffressourcen, sprich Menge an Rohstoff, die zwar wissenschaftlich erwiesen ist, jedoch nach Stand der heutigen Technik nicht abgebaut werden kann.</Description>
		</Property>
		<Property dataType="Float">
			<Title>Potential overall</Title>
			<Description language="DE">Gesamtes Rohstoffpotential, sprich Menge an Rohstoff, die ein Land insgesamt besitzt (schließt die Menge ein, die bereits abgebaut wurde).</Description>
		</Property>
		<Property dataType="Float">
			<Title>Potential remaining</Title>
			<Description language="DE">Verbleibendes Rohstoffpotential, sprich (gesamtes Potential MINUS kumulierte Foerderung), sprich die Menge, die nach bisherigem Abbau noch existiert.</Description>
		</Property>
	</TableStructure>
	<Entries>
		<Entry>
			<Value>AE</Value>
			<Value>51.7</Value>
			<Value>1090</Value>
			<Value>6090</Value>
			<Value>1500</Value>
			<Value>8680</Value>
			<Value>7590</Value>
		</Entry>
		<Entry>
			<Value>AF</Value>
			<Value>0.1</Value>
			<Value>57</Value>
			<Value>50</Value>
			<Value>350</Value>
			<Value>457</Value>
			<Value>400</Value>
		</Entry>
		<Entry>
			<Value>AL</Value>
			<Value>0.05</Value>
			<Value>8</Value>
			<Value>2</Value>
			<Value>50</Value>
			<Value>60</Value>
			<Value>52</Value>
		</Entry>
		<Entry>
			<Value>AM</Value>
			<Value>NODATA</Value>
			<Value>NODATA</Value>
			<Value>NODATA</Value>
			<Value>180</Value>
			<Value>180</Value>
			<Value>180</Value>
		</Entry>
		<Entry>
			<Value>AO</Value>
			<Value>0.8</Value>
			<Value>21</Value>
			<Value>297</Value>
			<Value>1200</Value>
			<Value>1518</Value>
			<Value>1497</Value>
		</Entry>
		<Entry>
			<Value>AR</Value>
			<Value>38.7</Value>
			<Value>1067</Value>
			<Value>333</Value>
			<Value>23710</Value>
			<Value>25110</Value>
			<Value>24043</Value>
		</Entry>
		<Entry>
			<Value>AT</Value>
			<Value>1.7</Value>
			<Value>95</Value>
			<Value>15</Value>
			<Value>820</Value>
			<Value>930</Value>
			<Value>835</Value>
		</Entry>
		<Entry>
			<Value>AU</Value>
			<Value>48.8</Value>
			<Value>984</Value>
			<Value>3759</Value>
			<Value>32430</Value>
			<Value>37174</Value>
			<Value>36189</Value>
		</Entry>
		<Entry>
			<Value>AZ</Value>
			<Value>16</Value>
			<Value>527</Value>
			<Value>991</Value>
			<Value>2000</Value>
			<Value>3518</Value>
			<Value>2991</Value>
		</Entry>
		<Entry>
			<Value>BB</Value>
			<Value>NODATA</Value>
			<Value>NODATA</Value>
			<Value>2</Value>
			<Value>150</Value>
			<Value>152</Value>
			<Value>152</Value>
		</Entry>
		<Entry>
			<Value>BD</Value>
			<Value>21.8</Value>
			<Value>302</Value>
			<Value>349</Value>
			<Value>800</Value>
			<Value>1451</Value>
			<Value>1149</Value>
		</Entry>
		<Entry>
			<Value>BG</Value>
			<Value>0.4</Value>
			<Value>7</Value>
			<Value>5</Value>
			<Value>575</Value>
			<Value>587</Value>
			<Value>580</Value>
		</Entry>
		<Entry>
			<Value>BH</Value>
			<Value>12.5</Value>
			<Value>250</Value>
			<Value>199</Value>
			<Value>200</Value>
			<Value>650</Value>
			<Value>399</Value>
		</Entry>
		<Entry>
			<Value>BJ</Value>
			<Value>NODATA</Value>
			<Value>NODATA</Value>
			<Value>1</Value>
			<Value>100</Value>
			<Value>101</Value>
			<Value>101</Value>
		</Entry>
		<Entry>
			<Value>BN</Value>
			<Value>12.5</Value>
			<Value>386</Value>
			<Value>288</Value>
			<Value>200</Value>
			<Value>874</Value>
			<Value>488</Value>
		</Entry>
		<Entry>
			<Value>BO</Value>
			<Value>18.7</Value>
			<Value>220</Value>
			<Value>282</Value>
			<Value>1620</Value>
			<Value>2121</Value>
			<Value>1902</Value>
		</Entry>
		<Entry>
			<Value>BR</Value>
			<Value>17.4</Value>
			<Value>245</Value>
			<Value>452</Value>
			<Value>18440</Value>
			<Value>19137</Value>
			<Value>18892</Value>
		</Entry>
		<Entry>
			<Value>BW</Value>
			<Value>NODATA</Value>
			<Value>NODATA</Value>
			<Value>NODATA</Value>
			<Value>1840</Value>
			<Value>1840</Value>
			<Value>1840</Value>
		</Entry>
		<Entry>
			<Value>BY</Value>
			<Value>0.2</Value>
			<Value>13</Value>
			<Value>3</Value>
			<Value>10</Value>
			<Value>25</Value>
			<Value>13</Value>
		</Entry>
		<Entry>
			<Value>BZ</Value>
			<Value>NODATA</Value>
			<Value>NODATA</Value>
			<Value>NODATA</Value>
			<Value>10</Value>
			<Value>10</Value>
			<Value>10</Value>
		</Entry>
		<Entry>
			<Value>CA</Value>
			<Value>156.5</Value>
			<Value>5678</Value>
			<Value>1930</Value>
			<Value>35883</Value>
			<Value>43492</Value>
			<Value>37813</Value>
		</Entry>
		<Entry>
			<Value>CD</Value>
			<Value>NODATA</Value>
			<Value>NODATA</Value>
			<Value>1</Value>
			<Value>10</Value>
			<Value>11</Value>
			<Value>11</Value>
		</Entry>
		<Entry>
			<Value>CG</Value>
			<Value>0.2</Value>
			<Value>NODATA</Value>
			<Value>124</Value>
			<Value>200</Value>
			<Value>324</Value>
			<Value>324</Value>
		</Entry>
		<Entry>
			<Value>CI</Value>
			<Value>1.7</Value>
			<Value>24</Value>
			<Value>16</Value>
			<Value>400</Value>
			<Value>440</Value>
			<Value>416</Value>
		</Entry>
		<Entry>
			<Value>CL</Value>
			<Value>1.2</Value>
			<Value>107</Value>
			<Value>41</Value>
			<Value>1510</Value>
			<Value>1658</Value>
			<Value>1551</Value>
		</Entry>
		<Entry>
			<Value>CM</Value>
			<Value>0.3</Value>
			<Value>NODATA</Value>
			<Value>153</Value>
			<Value>200</Value>
			<Value>353</Value>
			<Value>353</Value>
		</Entry>
		<Entry>
			<Value>CN</Value>
			<Value>110.7</Value>
			<Value>1263</Value>
			<Value>3096</Value>
			<Value>68980</Value>
			<Value>73339</Value>
			<Value>72076</Value>
		</Entry>
		<Entry>
			<Value>CO</Value>
			<Value>12</Value>
			<Value>231</Value>
			<Value>155</Value>
			<Value>2282</Value>
			<Value>2668</Value>
			<Value>2437</Value>
		</Entry>
		<Entry>
			<Value>CU</Value>
			<Value>1</Value>
			<Value>13</Value>
			<Value>71</Value>
			<Value>400</Value>
			<Value>484</Value>
			<Value>471</Value>
		</Entry>
		<Entry>
			<Value>CY</Value>
			<Value>NODATA</Value>
			<Value>NODATA</Value>
			<Value>NODATA</Value>
			<Value>250</Value>
			<Value>250</Value>
			<Value>250</Value>
		</Entry>
		<Entry>
			<Value>CZ</Value>
			<Value>0.3</Value>
			<Value>15</Value>
			<Value>5</Value>
			<Value>130</Value>
			<Value>150</Value>
			<Value>135</Value>
		</Entry>
		<Entry>
			<Value>DE</Value>
			<Value>12.1</Value>
			<Value>999</Value>
			<Value>123</Value>
			<Value>1870</Value>
			<Value>2992</Value>
			<Value>1993</Value>
		</Entry>
		<Entry>
			<Value>DK</Value>
			<Value>6.4</Value>
			<Value>173</Value>
			<Value>43</Value>
			<Value>950</Value>
			<Value>1166</Value>
			<Value>993</Value>
		</Entry>
		<Entry>
			<Value>DZ</Value>
			<Value>81.5</Value>
			<Value>2148</Value>
			<Value>4504</Value>
			<Value>26720</Value>
			<Value>33372</Value>
			<Value>31224</Value>
		</Entry>
		<Entry>
			<Value>EC</Value>
			<Value>0.5</Value>
			<Value>6</Value>
			<Value>7</Value>
			<Value>20</Value>
			<Value>33</Value>
			<Value>27</Value>
		</Entry>
		<Entry>
			<Value>EG</Value>
			<Value>60.9</Value>
			<Value>719</Value>
			<Value>2190</Value>
			<Value>10830</Value>
			<Value>13739</Value>
			<Value>13020</Value>
		</Entry>
		<Entry>
			<Value>EH</Value>
			<Value>NODATA</Value>
			<Value>NODATA</Value>
			<Value>NODATA</Value>
			<Value>228</Value>
			<Value>228</Value>
			<Value>228</Value>
		</Entry>
		<Entry>
			<Value>ER</Value>
			<Value>NODATA</Value>
			<Value>NODATA</Value>
			<Value>NODATA</Value>
			<Value>100</Value>
			<Value>100</Value>
			<Value>100</Value>
		</Entry>
		<Entry>
			<Value>ES</Value>
			<Value>0.1</Value>
			<Value>11</Value>
			<Value>3</Value>
			<Value>2435</Value>
			<Value>2449</Value>
			<Value>2438</Value>
		</Entry>
		<Entry>
			<Value>ET</Value>
			<Value>NODATA</Value>
			<Value>NODATA</Value>
			<Value>28</Value>
			<Value>20</Value>
			<Value>48</Value>
			<Value>48</Value>
		</Entry>
		<Entry>
			<Value>FK</Value>
			<Value>NODATA</Value>
			<Value>NODATA</Value>
			<Value>NODATA</Value>
			<Value>1500</Value>
			<Value>1500</Value>
			<Value>1500</Value>
		</Entry>
		<Entry>
			<Value>FR</Value>
			<Value>0.5</Value>
			<Value>228</Value>
			<Value>11</Value>
			<Value>3984</Value>
			<Value>4223</Value>
			<Value>3995</Value>
		</Entry>
		<Entry>
			<Value>GA</Value>
			<Value>0.2</Value>
			<Value>5</Value>
			<Value>27</Value>
			<Value>600</Value>
			<Value>632</Value>
			<Value>627</Value>
		</Entry>
		<Entry>
			<Value>GB</Value>
			<Value>41.1</Value>
			<Value>2421</Value>
			<Value>461</Value>
			<Value>1849</Value>
			<Value>4731</Value>
			<Value>2310</Value>
		</Entry>
		<Entry>
			<Value>GD</Value>
			<Value>NODATA</Value>
			<Value>NODATA</Value>
			<Value>NODATA</Value>
			<Value>25</Value>
			<Value>25</Value>
			<Value>25</Value>
		</Entry>
		<Entry>
			<Value>GE</Value>
			<Value>0.025</Value>
			<Value>3</Value>
			<Value>8</Value>
			<Value>102</Value>
			<Value>113</Value>
			<Value>110</Value>
		</Entry>
		<Entry>
			<Value>GH</Value>
			<Value>NODATA</Value>
			<Value>NODATA</Value>
			<Value>27</Value>
			<Value>300</Value>
			<Value>327</Value>
			<Value>327</Value>
		</Entry>
		<Entry>
			<Value>GL</Value>
			<Value>NODATA</Value>
			<Value>NODATA</Value>
			<Value>NODATA</Value>
			<Value>3900</Value>
			<Value>3900</Value>
			<Value>3900</Value>
		</Entry>
		<Entry>
			<Value>GM</Value>
			<Value>NODATA</Value>
			<Value>NODATA</Value>
			<Value>NODATA</Value>
			<Value>25</Value>
			<Value>25</Value>
			<Value>25</Value>
		</Entry>
		<Entry>
			<Value>GN</Value>
			<Value>NODATA</Value>
			<Value>NODATA</Value>
			<Value>NODATA</Value>
			<Value>200</Value>
			<Value>200</Value>
			<Value>200</Value>
		</Entry>
		<Entry>
			<Value>GQ</Value>
			<Value>6.5</Value>
			<Value>35</Value>
			<Value>121</Value>
			<Value>120</Value>
			<Value>276</Value>
			<Value>241</Value>
		</Entry>
		<Entry>
			<Value>GR</Value>
			<Value>0.025</Value>
			<Value>1</Value>
			<Value>1</Value>
			<Value>10</Value>
			<Value>12</Value>
			<Value>11</Value>
		</Entry>
		<Entry>
			<Value>GT</Value>
			<Value>NODATA</Value>
			<Value>NODATA</Value>
			<Value>NODATA</Value>
			<Value>10</Value>
			<Value>10</Value>
			<Value>10</Value>
		</Entry>
		<Entry>
			<Value>GW</Value>
			<Value>NODATA</Value>
			<Value>NODATA</Value>
			<Value>NODATA</Value>
			<Value>50</Value>
			<Value>50</Value>
			<Value>50</Value>
		</Entry>
		<Entry>
			<Value>GY</Value>
			<Value>NODATA</Value>
			<Value>NODATA</Value>
			<Value>NODATA</Value>
			<Value>100</Value>
			<Value>100</Value>
			<Value>100</Value>
		</Entry>
		<Entry>
			<Value>HR</Value>
			<Value>1.9</Value>
			<Value>68</Value>
			<Value>24</Value>
			<Value>50</Value>
			<Value>142</Value>
			<Value>74</Value>
		</Entry>
		<Entry>
			<Value>HT</Value>
			<Value>NODATA</Value>
			<Value>NODATA</Value>
			<Value>NODATA</Value>
			<Value>50</Value>
			<Value>50</Value>
			<Value>50</Value>
		</Entry>
		<Entry>
			<Value>HU</Value>
			<Value>2.2</Value>
			<Value>225</Value>
			<Value>8</Value>
			<Value>347</Value>
			<Value>580</Value>
			<Value>355</Value>
		</Entry>
		<Entry>
			<Value>ID</Value>
			<Value>76.7</Value>
			<Value>1937</Value>
			<Value>2927</Value>
			<Value>10480</Value>
			<Value>15344</Value>
			<Value>13407</Value>
		</Entry>
		<Entry>
			<Value>IE</Value>
			<Value>0.4</Value>
			<Value>56</Value>
			<Value>25</Value>
			<Value>50</Value>
			<Value>131</Value>
			<Value>75</Value>
		</Entry>
		<Entry>
			<Value>IL</Value>
			<Value>2.5</Value>
			<Value>17</Value>
			<Value>269</Value>
			<Value>2000</Value>
			<Value>2286</Value>
			<Value>2269</Value>
		</Entry>
		<Entry>
			<Value>IN</Value>
			<Value>41.9</Value>
			<Value>695</Value>
			<Value>1330</Value>
			<Value>6530</Value>
			<Value>8555</Value>
			<Value>7860</Value>
		</Entry>
		<Entry>
			<Value>IQ</Value>
			<Value>5.8</Value>
			<Value>113</Value>
			<Value>3588</Value>
			<Value>4000</Value>
			<Value>7701</Value>
			<Value>7588</Value>
		</Entry>
		<Entry>
			<Value>IR</Value>
			<Value>158.2</Value>
			<Value>2048</Value>
			<Value>33620</Value>
			<Value>11000</Value>
			<Value>46668</Value>
			<Value>44620</Value>
		</Entry>
		<Entry>
			<Value>IT</Value>
			<Value>7.8</Value>
			<Value>736</Value>
			<Value>55</Value>
			<Value>405</Value>
			<Value>1195</Value>
			<Value>459</Value>
		</Entry>
		<Entry>
			<Value>JO</Value>
			<Value>0.2</Value>
			<Value>5</Value>
			<Value>6</Value>
			<Value>350</Value>
			<Value>361</Value>
			<Value>356</Value>
		</Entry>
		<Entry>
			<Value>JP</Value>
			<Value>3.2</Value>
			<Value>130</Value>
			<Value>21</Value>
			<Value>5</Value>
			<Value>156</Value>
			<Value>26</Value>
		</Entry>
		<Entry>
			<Value>KE</Value>
			<Value>NODATA</Value>
			<Value>NODATA</Value>
			<Value>NODATA</Value>
			<Value>600</Value>
			<Value>600</Value>
			<Value>600</Value>
		</Entry>
		<Entry>
			<Value>KG</Value>
			<Value>0.025</Value>
			<Value>7</Value>
			<Value>6</Value>
			<Value>20</Value>
			<Value>33</Value>
			<Value>26</Value>
		</Entry>
		<Entry>
			<Value>KH</Value>
			<Value>NODATA</Value>
			<Value>NODATA</Value>
			<Value>NODATA</Value>
			<Value>50</Value>
			<Value>50</Value>
			<Value>50</Value>
		</Entry>
		<Entry>
			<Value>KR</Value>
			<Value>0.4</Value>
			<Value>NODATA</Value>
			<Value>5</Value>
			<Value>50</Value>
			<Value>55</Value>
			<Value>55</Value>
		</Entry>
		<Entry>
			<Value>KW</Value>
			<Value>14.5</Value>
			<Value>305</Value>
			<Value>1784</Value>
			<Value>500</Value>
			<Value>2589</Value>
			<Value>2284</Value>
		</Entry>
		<Entry>
			<Value>KZ</Value>
			<Value>29.1</Value>
			<Value>471</Value>
			<Value>1950</Value>
			<Value>3700</Value>
			<Value>6121</Value>
			<Value>5650</Value>
		</Entry>
		<Entry>
			<Value>LA</Value>
			<Value>NODATA</Value>
			<Value>NODATA</Value>
			<Value>NODATA</Value>
			<Value>5</Value>
			<Value>5</Value>
			<Value>5</Value>
		</Entry>
		<Entry>
			<Value>LB</Value>
			<Value>NODATA</Value>
			<Value>NODATA</Value>
			<Value>NODATA</Value>
			<Value>850</Value>
			<Value>850</Value>
			<Value>850</Value>
		</Entry>
		<Entry>
			<Value>LK</Value>
			<Value>NODATA</Value>
			<Value>NODATA</Value>
			<Value>NODATA</Value>
			<Value>300</Value>
			<Value>300</Value>
			<Value>300</Value>
		</Entry>
		<Entry>
			<Value>LR</Value>
			<Value>NODATA</Value>
			<Value>NODATA</Value>
			<Value>NODATA</Value>
			<Value>200</Value>
			<Value>200</Value>
			<Value>200</Value>
		</Entry>
		<Entry>
			<Value>LT</Value>
			<Value>NODATA</Value>
			<Value>NODATA</Value>
			<Value>NODATA</Value>
			<Value>0.25</Value>
			<Value>0.025</Value>
			<Value>0.25</Value>
		</Entry>
		<Entry>
			<Value>LY</Value>
			<Value>12.2</Value>
			<Value>282</Value>
			<Value>1547</Value>
			<Value>4650</Value>
			<Value>6479</Value>
			<Value>6197</Value>
		</Entry>
		<Entry>
			<Value>MA</Value>
			<Value>0.1</Value>
			<Value>2</Value>
			<Value>1</Value>
			<Value>2220</Value>
			<Value>2224</Value>
			<Value>2221</Value>
		</Entry>
		<Entry>
			<Value>MD</Value>
			<Value>NODATA</Value>
			<Value>NODATA</Value>
			<Value>NODATA</Value>
			<Value>20</Value>
			<Value>20</Value>
			<Value>20</Value>
		</Entry>
		<Entry>
			<Value>MG</Value>
			<Value>NODATA</Value>
			<Value>NODATA</Value>
			<Value>2</Value>
			<Value>4700</Value>
			<Value>4702</Value>
			<Value>4702</Value>
		</Entry>
		<Entry>
			<Value>MM</Value>
			<Value>11.8</Value>
			<Value>158</Value>
			<Value>283</Value>
			<Value>2000</Value>
			<Value>2441</Value>
			<Value>2283</Value>
		</Entry>
		<Entry>
			<Value>MN</Value>
			<Value>NODATA</Value>
			<Value>NODATA</Value>
			<Value>NODATA</Value>
			<Value>133</Value>
			<Value>133</Value>
			<Value>133</Value>
		</Entry>
		<Entry>
			<Value>MR</Value>
			<Value>NODATA</Value>
			<Value>NODATA</Value>
			<Value>28</Value>
			<Value>200</Value>
			<Value>228</Value>
			<Value>228</Value>
		</Entry>
		<Entry>
			<Value>MT</Value>
			<Value>NODATA</Value>
			<Value>NODATA</Value>
			<Value>NODATA</Value>
			<Value>10</Value>
			<Value>10</Value>
			<Value>10</Value>
		</Entry>
		<Entry>
			<Value>MX</Value>
			<Value>47</Value>
			<Value>1524</Value>
			<Value>360</Value>
			<Value>17770</Value>
			<Value>19654</Value>
			<Value>18130</Value>
		</Entry>
		<Entry>
			<Value>MY</Value>
			<Value>63</Value>
			<Value>1131</Value>
			<Value>2389</Value>
			<Value>1900</Value>
			<Value>5420</Value>
			<Value>4289</Value>
		</Entry>
		<Entry>
			<Value>MZ</Value>
			<Value>3.4</Value>
			<Value>25</Value>
			<Value>127</Value>
			<Value>5200</Value>
			<Value>5353</Value>
			<Value>5327</Value>
		</Entry>
		<Entry>
			<Value>NA</Value>
			<Value>NODATA</Value>
			<Value>NODATA</Value>
			<Value>62</Value>
			<Value>250</Value>
			<Value>312</Value>
			<Value>312</Value>
		</Entry>
		<Entry>
			<Value>NE</Value>
			<Value>NODATA</Value>
			<Value>NODATA</Value>
			<Value>NODATA</Value>
			<Value>250</Value>
			<Value>250</Value>
			<Value>250</Value>
		</Entry>
		<Entry>
			<Value>NG</Value>
			<Value>37.9</Value>
			<Value>414</Value>
			<Value>5118</Value>
			<Value>3000</Value>
			<Value>8532</Value>
			<Value>8118</Value>
		</Entry>
		<Entry>
			<Value>NL</Value>
			<Value>80.1</Value>
			<Value>3377</Value>
			<Value>1130</Value>
			<Value>1505</Value>
			<Value>6012</Value>
			<Value>2635</Value>
		</Entry>
		<Entry>
			<Value>NO</Value>
			<Value>114.8</Value>
			<Value>1767</Value>
			<Value>2090</Value>
			<Value>1820</Value>
			<Value>5677</Value>
			<Value>3910</Value>
		</Entry>
		<Entry>
			<Value>NZ</Value>
			<Value>4.6</Value>
			<Value>150</Value>
			<Value>29</Value>
			<Value>353</Value>
			<Value>533</Value>
			<Value>382</Value>
		</Entry>
		<Entry>
			<Value>OM</Value>
			<Value>29</Value>
			<Value>342</Value>
			<Value>950</Value>
			<Value>1650</Value>
			<Value>2942</Value>
			<Value>2600</Value>
		</Entry>
		<Entry>
			<Value>PE</Value>
			<Value>12.7</Value>
			<Value>91</Value>
			<Value>359</Value>
			<Value>200</Value>
			<Value>650</Value>
			<Value>559</Value>
		</Entry>
		<Entry>
			<Value>PG</Value>
			<Value>0.1</Value>
			<Value>3</Value>
			<Value>442</Value>
			<Value>1000</Value>
			<Value>1445</Value>
			<Value>1442</Value>
		</Entry>
		<Entry>
			<Value>PH</Value>
			<Value>3.8</Value>
			<Value>33</Value>
			<Value>87</Value>
			<Value>502</Value>
			<Value>622</Value>
			<Value>589</Value>
		</Entry>
		<Entry>
			<Value>PK</Value>
			<Value>41.3</Value>
			<Value>758</Value>
			<Value>766</Value>
			<Value>4570</Value>
			<Value>6094</Value>
			<Value>5336</Value>
		</Entry>
		<Entry>
			<Value>PL</Value>
			<Value>4.5</Value>
			<Value>253</Value>
			<Value>88</Value>
			<Value>797</Value>
			<Value>1138</Value>
			<Value>885</Value>
		</Entry>
		<Entry>
			<Value>PR</Value>
			<Value>NODATA</Value>
			<Value>NODATA</Value>
			<Value>NODATA</Value>
			<Value>30</Value>
			<Value>30</Value>
			<Value>30</Value>
		</Entry>
		<Entry>
			<Value>PS</Value>
			<Value>NODATA</Value>
			<Value>NODATA</Value>
			<Value>30</Value>
			<Value>350</Value>
			<Value>380</Value>
			<Value>380</Value>
		</Entry>
		<Entry>
			<Value>PT</Value>
			<Value>NODATA</Value>
			<Value>NODATA</Value>
			<Value>NODATA</Value>
			<Value>40</Value>
			<Value>40</Value>
			<Value>40</Value>
		</Entry>
		<Entry>
			<Value>PY</Value>
			<Value>NODATA</Value>
			<Value>NODATA</Value>
			<Value>NODATA</Value>
			<Value>2420</Value>
			<Value>2420</Value>
			<Value>2420</Value>
		</Entry>
		<Entry>
			<Value>QA</Value>
			<Value>157</Value>
			<Value>1109</Value>
			<Value>25069</Value>
			<Value>2000</Value>
			<Value>28178</Value>
			<Value>27069</Value>
		</Entry>
		<Entry>
			<Value>RO</Value>
			<Value>10.9</Value>
			<Value>1276</Value>
			<Value>102</Value>
			<Value>1590</Value>
			<Value>2968</Value>
			<Value>1692</Value>
		</Entry>
		<Entry>
			<Value>RS</Value>
			<Value>0.5</Value>
			<Value>32</Value>
			<Value>48</Value>
			<Value>10</Value>
			<Value>90</Value>
			<Value>58</Value>
		</Entry>
		<Entry>
			<Value>RU</Value>
			<Value>609.7</Value>
			<Value>20453</Value>
			<Value>46000</Value>
			<Value>142050</Value>
			<Value>208503</Value>
			<Value>188050</Value>
		</Entry>
		<Entry>
			<Value>RW</Value>
			<Value>NODATA</Value>
			<Value>NODATA</Value>
			<Value>NODATA</Value>
			<Value>50</Value>
			<Value>50</Value>
			<Value>50</Value>
		</Entry>
		<Entry>
			<Value>SA</Value>
			<Value>95.2</Value>
			<Value>1580</Value>
			<Value>8151</Value>
			<Value>24664</Value>
			<Value>34395</Value>
			<Value>32815</Value>
		</Entry>
		<Entry>
			<Value>SC</Value>
			<Value>NODATA</Value>
			<Value>NODATA</Value>
			<Value>NODATA</Value>
			<Value>600</Value>
			<Value>600</Value>
			<Value>600</Value>
		</Entry>
		<Entry>
			<Value>SD</Value>
			<Value>NODATA</Value>
			<Value>NODATA</Value>
			<Value>85</Value>
			<Value>250</Value>
			<Value>335</Value>
			<Value>335</Value>
		</Entry>
		<Entry>
			<Value>SE</Value>
			<Value>NODATA</Value>
			<Value>NODATA</Value>
			<Value>NODATA</Value>
			<Value>280</Value>
			<Value>280</Value>
			<Value>280</Value>
		</Entry>
		<Entry>
			<Value>SI</Value>
			<Value>0.025</Value>
			<Value>NODATA</Value>
			<Value>1</Value>
			<Value>15</Value>
			<Value>16</Value>
			<Value>16</Value>
		</Entry>
		<Entry>
			<Value>SK</Value>
			<Value>0.2</Value>
			<Value>26</Value>
			<Value>13</Value>
			<Value>10</Value>
			<Value>49</Value>
			<Value>23</Value>
		</Entry>
		<Entry>
			<Value>SL</Value>
			<Value>NODATA</Value>
			<Value>NODATA</Value>
			<Value>NODATA</Value>
			<Value>300</Value>
			<Value>300</Value>
			<Value>300</Value>
		</Entry>
		<Entry>
			<Value>SN</Value>
			<Value>NODATA</Value>
			<Value>NODATA</Value>
			<Value>10</Value>
			<Value>200</Value>
			<Value>210</Value>
			<Value>210</Value>
		</Entry>
		<Entry>
			<Value>SO</Value>
			<Value>NODATA</Value>
			<Value>NODATA</Value>
			<Value>6</Value>
			<Value>400</Value>
			<Value>406</Value>
			<Value>406</Value>
		</Entry>
		<Entry>
			<Value>SR</Value>
			<Value>NODATA</Value>
			<Value>NODATA</Value>
			<Value>NODATA</Value>
			<Value>300</Value>
			<Value>300</Value>
			<Value>300</Value>
		</Entry>
		<Entry>
			<Value>ST</Value>
			<Value>NODATA</Value>
			<Value>NODATA</Value>
			<Value>NODATA</Value>
			<Value>100</Value>
			<Value>100</Value>
			<Value>100</Value>
		</Entry>
		<Entry>
			<Value>SY</Value>
			<Value>6.7</Value>
			<Value>127</Value>
			<Value>285</Value>
			<Value>300</Value>
			<Value>712</Value>
			<Value>585</Value>
		</Entry>
		<Entry>
			<Value>TD</Value>
			<Value>NODATA</Value>
			<Value>NODATA</Value>
			<Value>NODATA</Value>
			<Value>200</Value>
			<Value>200</Value>
			<Value>200</Value>
		</Entry>
		<Entry>
			<Value>TG</Value>
			<Value>NODATA</Value>
			<Value>NODATA</Value>
			<Value>NODATA</Value>
			<Value>100</Value>
			<Value>100</Value>
			<Value>100</Value>
		</Entry>
		<Entry>
			<Value>TH</Value>
			<Value>41.4</Value>
			<Value>490</Value>
			<Value>256</Value>
			<Value>740</Value>
			<Value>1486</Value>
			<Value>996</Value>
		</Entry>
		<Entry>
			<Value>TJ</Value>
			<Value>0.025</Value>
			<Value>9</Value>
			<Value>6</Value>
			<Value>100</Value>
			<Value>114</Value>
			<Value>106</Value>
		</Entry>
		<Entry>
			<Value>TL</Value>
			<Value>NODATA</Value>
			<Value>NODATA</Value>
			<Value>101</Value>
			<Value>300</Value>
			<Value>401</Value>
			<Value>401</Value>
		</Entry>
		<Entry>
			<Value>TM</Value>
			<Value>64.4</Value>
			<Value>2431</Value>
			<Value>10000</Value>
			<Value>15000</Value>
			<Value>27431</Value>
			<Value>25000</Value>
		</Entry>
		<Entry>
			<Value>TN</Value>
			<Value>2.7</Value>
			<Value>47</Value>
			<Value>65</Value>
			<Value>800</Value>
			<Value>912</Value>
			<Value>865</Value>
		</Entry>
		<Entry>
			<Value>TR</Value>
			<Value>0.7</Value>
			<Value>13</Value>
			<Value>7</Value>
			<Value>1153</Value>
			<Value>1173</Value>
			<Value>1160</Value>
		</Entry>
		<Entry>
			<Value>TT</Value>
			<Value>42.2</Value>
			<Value>545</Value>
			<Value>375</Value>
			<Value>500</Value>
			<Value>1420</Value>
			<Value>875</Value>
		</Entry>
		<Entry>
			<Value>TW</Value>
			<Value>0.4</Value>
			<Value>51</Value>
			<Value>6</Value>
			<Value>5</Value>
			<Value>62</Value>
			<Value>11</Value>
		</Entry>
		<Entry>
			<Value>TZ</Value>
			<Value>0.9</Value>
			<Value>NODATA</Value>
			<Value>37</Value>
			<Value>1400</Value>
			<Value>1437</Value>
			<Value>1437</Value>
		</Entry>
		<Entry>
			<Value>UA</Value>
			<Value>18.6</Value>
			<Value>1965</Value>
			<Value>969</Value>
			<Value>5930</Value>
			<Value>8864</Value>
			<Value>6899</Value>
		</Entry>
		<Entry>
			<Value>UG</Value>
			<Value>NODATA</Value>
			<Value>NODATA</Value>
			<Value>14</Value>
			<Value>NODATA</Value>
			<Value>14</Value>
			<Value>14</Value>
		</Entry>
		<Entry>
			<Value>US</Value>
			<Value>681.5</Value>
			<Value>32868</Value>
			<Value>8495</Value>
			<Value>53850</Value>
			<Value>95213</Value>
			<Value>62345</Value>
		</Entry>
		<Entry>
			<Value>UY</Value>
			<Value>NODATA</Value>
			<Value>NODATA</Value>
			<Value>NODATA</Value>
			<Value>828</Value>
			<Value>828</Value>
			<Value>828</Value>
		</Entry>
		<Entry>
			<Value>UZ</Value>
			<Value>57.7</Value>
			<Value>2136</Value>
			<Value>1661</Value>
			<Value>1500</Value>
			<Value>5297</Value>
			<Value>3161</Value>
		</Entry>
		<Entry>
			<Value>VE</Value>
			<Value>32.8</Value>
			<Value>1051</Value>
			<Value>5528</Value>
			<Value>7230</Value>
			<Value>13809</Value>
			<Value>12758</Value>
		</Entry>
		<Entry>
			<Value>VN</Value>
			<Value>9.4</Value>
			<Value>81</Value>
			<Value>617</Value>
			<Value>1392</Value>
			<Value>2090</Value>
			<Value>2009</Value>
		</Entry>
		<Entry>
			<Value>YE</Value>
			<Value>7.8</Value>
			<Value>26</Value>
			<Value>479</Value>
			<Value>500</Value>
			<Value>1005</Value>
			<Value>979</Value>
		</Entry>
		<Entry>
			<Value>ZA</Value>
			<Value>1.4</Value>
			<Value>39</Value>
			<Value>16</Value>
			<Value>12330</Value>
			<Value>12385</Value>
			<Value>12346</Value>
		</Entry>
		<Entry>
			<Value>ZW</Value>
			<Value>NODATA</Value>
			<Value>NODATA</Value>
			<Value>NODATA</Value>
			<Value>10</Value>
			<Value>10</Value>
			<Value>10</Value>
		</Entry>
	</Entries>
</Dataset>
